gradescopecalendar/__init__.py
gradescopecalendar/gradescopecalendar.py
gradescopecalendar/calendars/__init__.py
gradescopecalendar/calendars/gcal.py
gradescopecalendar/calendars/ical.py
gradescopecalendar/gradescope/__init__.py
gradescopecalendar/gradescope/account.py
gradescopecalendar/gradescope/assignment.py
gradescopecalendar/gradescope/course.py
gradescopecalendar/gradescope/pyscope.py
gradescopecalendar-0.0.9.dist-info/LICENSE
gradescopecalendar-0.0.9.dist-info/METADATA
gradescopecalendar-0.0.9.dist-info/WHEEL
gradescopecalendar-0.0.9.dist-info/top_level.txt
gradescopecalendar-0.0.9.dist-info/RECORD
