Metadata-Version: 2.1
Name: gradescopecalendar
Version: 0.0.9
Summary: Unofficial calendar integration for Gradescope
Home-page: https://github.com/calvinatian/gradescope-calendar
Author: Calvin
Author-email: calvinaatian@gmail.com
Project-URL: Bug Tracker, https://github.com/calvinatian/gradescope-calendar/issues
Classifier: Programming Language :: Python :: 3
Classifier: License :: OSI Approved :: GNU Affero General Public License v3
Classifier: Operating System :: OS Independent
Requires-Python: >=3.7
License-File: LICENSE
Requires-Dist: bs4
Requires-Dist: requests
Requires-Dist: icalendar
Requires-Dist: google-api-core
Requires-Dist: google-api-python-client
Requires-Dist: google-auth
Requires-Dist: google-auth-httplib2
Requires-Dist: google-auth-oauthlib
Requires-Dist: googleapis-common-protos
